arg_types.py
venmo.py
venmo_cli-0.1.0.dist-info/LICENSE.txt
venmo_cli-0.1.0.dist-info/METADATA
venmo_cli-0.1.0.dist-info/WHEEL
venmo_cli-0.1.0.dist-info/entry_points.txt
venmo_cli-0.1.0.dist-info/top_level.txt
venmo_cli-0.1.0.dist-info/RECORD
