Metadata-Version: 2.1
Name: venmo-cli
Version: 0.1.0
Summary: A simple CLI for Venmo
Home-page: https://github.com/AstroCB/venmo-cli
Author: Cameron Bernhardt
Author-email: me@cameronbernhardt.com
License-File: LICENSE.txt
Requires-Dist: black (==22.12.0)
Requires-Dist: certifi (==2022.12.7)
Requires-Dist: charset-normalizer (==2.1.1)
Requires-Dist: click (==8.1.3)
Requires-Dist: idna (==3.4)
Requires-Dist: mypy-extensions (==0.4.3)
Requires-Dist: pathspec (==0.10.3)
Requires-Dist: platformdirs (==2.6.0)
Requires-Dist: requests (==2.28.1)
Requires-Dist: tomli (==2.0.1)
Requires-Dist: typing-extensions (==4.4.0)
Requires-Dist: urllib3 (==1.26.13)
Requires-Dist: venmo-api (==0.3.1)
